{
    "gridmap": [
        [
            0.8647975870165865,
            0.855302514932059,
            0.8110233987843422,
            0.2614463614164766,
            0.0771994577184214,
            0.9464657804460633
        ],
        [
            0.6137916910471019,
            0.00263075362629972,
            0.9104071780658378,
            0.9848034752375554,
            0.2862966041661704,
            0.8136611230389795
        ],
        [
            0.08240794388130823,
            0.4382800473034214,
            0.8177037747448075,
            0.40873333268977363,
            0.5177497071869771,
            0.11703988347506633
        ],
        [
            0.8140065192501118,
            0.4978674083325122,
            0.24827919488667194,
            0.7766861560008684,
            0.9792282891895626,
            0.53834323407629
        ],
        [
            0.7371502226207836,
            0.9927606888483627,
            0.03012749637532397,
            0.5989776523667713,
            0.9672952777915866,
            0.11733657384331686
        ],
        [
            0.2231014949939203,
            0.5502283889833729,
            0.722327310719796,
            0.5527524153948293,
            0.5477017956423661,
            0.0515388294743615
        ]
    ],
    "0": {
        "position": [
            [
                1,
                1
            ],
            [
                2,
                2
            ],
            [
                3,
                3
            ]
        ],
        "values": 3.8850079720129833,
        "decision": [
            [
                [
                    0,
                    -1
                ],
                [
                    -1,
                    0
                ],
                [
                    0,
                    1
                ]
            ],
            [
                [
                    0,
                    0
                ],
                [
                    -1,
                    0
                ],
                [
                    0,
                    1
                ]
            ],
            [
                [
                    0,
                    0
                ],
                [
                    0,
                    1
                ],
                [
                    1,
                    0
                ]
            ]
        ],
        "gain": [
            0.3068958455235509,
            0.40885188737240374,
            0.3883430780004342
        ]
    },
    "1": {
        "position": [
            [
                1,
                0
            ],
            [
                2,
                2
            ],
            [
                3,
                3
            ]
        ],
        "values": 3.7321185555015397,
        "decision": [
            [
                [
                    -1,
                    0
                ],
                [
                    0,
                    1
                ],
                [
                    0,
                    1
                ]
            ],
            [
                [
                    -1,
                    0
                ],
                [
                    0,
                    1
                ],
                [
                    0,
                    0
                ]
            ],
            [
                [
                    0,
                    1
                ],
                [
                    1,
                    0
                ],
                [
                    0,
                    -1
                ]
            ]
        ],
        "gain": [
            0.43239879350829324,
            0.4552035890329189,
            0.4896141445947813
        ]
    },
    "2": {
        "position": [
            [
                0,
                0
            ],
            [
                1,
                2
            ],
            [
                3,
                4
            ]
        ],
        "values": 3.162658025372606,
        "decision": [
            [
                [
                    0,
                    1
                ],
                [
                    0,
                    1
                ],
                [
                    1,
                    0
                ]
            ],
            [
                [
                    0,
                    1
                ],
                [
                    0,
                    1
                ],
                [
                    0,
                    1
                ]
            ],
            [
                [
                    1,
                    0
                ],
                [
                    0,
                    -1
                ],
                [
                    1,
                    0
                ]
            ]
        ],
        "gain": [
            0.4276512574660295,
            0.4924017376187777,
            0.4836476388957933
        ]
    },
    "3": {
        "position": [
            [
                0,
                1
            ],
            [
                1,
                3
            ],
            [
                4,
                4
            ]
        ],
        "values": 2.8395548057843243,
        "decision": [
            [
                [
                    0,
                    1
                ],
                [
                    1,
                    0
                ],
                [
                    0,
                    1
                ]
            ],
            [
                [
                    0,
                    1
                ],
                [
                    0,
                    1
                ],
                [
                    -1,
                    0
                ]
            ],
            [
                [
                    0,
                    -1
                ],
                [
                    1,
                    0
                ],
                [
                    0,
                    -1
                ]
            ]
        ],
        "gain": [
            0.4055116993921711,
            0.1431483020830852,
            0.2994888261833856
        ]
    },
    "4": {
        "position": [
            [
                0,
                2
            ],
            [
                1,
                4
            ],
            [
                4,
                3
            ]
        ],
        "values": 2.7075032840737716,
        "decision": [
            [
                [
                    1,
                    0
                ],
                [
                    0,
                    1
                ],
                [
                    1,
                    0
                ]
            ],
            [
                [
                    0,
                    1
                ],
                [
                    -1,
                    0
                ],
                [
                    0,
                    0
                ]
            ],
            [
                [
                    1,
                    0
                ],
                [
                    0,
                    -1
                ],
                [
                    0,
                    -1
                ]
            ]
        ],
        "gain": [
            0.22760179451645945,
            0.40683056151948976,
            0.27637620769741467
        ]
    },
    "5": {
        "position": [
            [
                1,
                2
            ],
            [
                1,
                5
            ],
            [
                5,
                3
            ]
        ],
        "values": 2.7553651991178225,
        "decision": [
            [
                [
                    0,
                    1
                ],
                [
                    1,
                    0
                ],
                [
                    0,
                    1
                ]
            ],
            [
                [
                    -1,
                    0
                ],
                [
                    1,
                    0
                ],
                [
                    -1,
                    0
                ]
            ],
            [
                [
                    0,
                    -1
                ],
                [
                    0,
                    -1
                ],
                [
                    -1,
                    0
                ]
            ]
        ],
        "gain": [
            0.24620086880938885,
            0.47323289022303167,
            0.361163655359898
        ]
    },
    "6": {
        "position": [
            [
                1,
                3
            ],
            [
                0,
                5
            ],
            [
                5,
                2
            ]
        ],
        "values": 2.406458190889044,
        "decision": [
            [
                [
                    1,
                    0
                ],
                [
                    0,
                    1
                ],
                [
                    1,
                    0
                ]
            ],
            [
                [
                    1,
                    0
                ],
                [
                    -1,
                    0
                ],
                [
                    0,
                    0
                ]
            ],
            [
                [
                    0,
                    -1
                ],
                [
                    -1,
                    0
                ],
                [
                    0,
                    -1
                ]
            ]
        ],
        "gain": [
            0.20436666634488682,
            0.20341528075974488,
            0.27511419449168645
        ]
    },
    "7": {
        "position": [
            [
                2,
                3
            ],
            [
                1,
                5
            ],
            [
                5,
                1
            ]
        ],
        "values": 2.5197144637962197,
        "decision": [
            [
                [
                    0,
                    -1
                ],
                [
                    0,
                    -1
                ],
                [
                    1,
                    0
                ]
            ],
            [
                [
                    0,
                    -1
                ],
                [
                    1,
                    0
                ],
                [
                    1,
                    0
                ]
            ],
            [
                [
                    -1,
                    0
                ],
                [
                    0,
                    -1
                ],
                [
                    -1,
                    0
                ]
            ]
        ],
        "gain": [
            0.20442594368620187,
            0.0715741510415426,
            0.49638034442418133
        ]
    },
    "8": {
        "position": [
            [
                2,
                2
            ],
            [
                1,
                4
            ],
            [
                4,
                1
            ]
        ],
        "values": 2.4681974437070573,
        "decision": [
            [
                [
                    0,
                    -1
                ],
                [
                    1,
                    0
                ],
                [
                    1,
                    0
                ]
            ],
            [
                [
                    1,
                    0
                ],
                [
                    1,
                    0
                ],
                [
                    0,
                    1
                ]
            ],
            [
                [
                    0,
                    -1
                ],
                [
                    -1,
                    0
                ],
                [
                    0,
                    0
                ]
            ]
        ],
        "gain": [
            0.2191400236517107,
            0.25887485359348855,
            0.3685751113103918
        ]
    },
    "9": {
        "position": [
            [
                2,
                1
            ],
            [
                2,
                4
            ],
            [
                4,
                0
            ]
        ],
        "values": 2.18995520828344,
        "decision": [
            [
                [
                    1,
                    0
                ],
                [
                    1,
                    0
                ],
                [
                    1,
                    0
                ]
            ],
            [
                [
                    1,
                    0
                ],
                [
                    1,
                    0
                ],
                [
                    1,
                    0
                ]
            ],
            [
                [
                    -1,
                    0
                ],
                [
                    1,
                    0
                ],
                [
                    -1,
                    0
                ]
            ]
        ],
        "gain": [
            0.2489337041662561,
            0.24480707229739065,
            0.4070032596250559
        ]
    },
    "10": {
        "position": [
            [
                3,
                1
            ],
            [
                3,
                4
            ],
            [
                3,
                0
            ]
        ],
        "values": 1.7578977283328474,
        "decision": [
            [
                [
                    0,
                    1
                ],
                [
                    0,
                    1
                ],
                [
                    1,
                    0
                ]
            ],
            [
                [
                    1,
                    0
                ],
                [
                    1,
                    0
                ],
                [
                    0,
                    -1
                ]
            ],
            [
                [
                    0,
                    0
                ],
                [
                    1,
                    0
                ],
                [
                    0,
                    1
                ]
            ]
        ],
        "gain": [
            0.12413959744333597,
            0.24182381944789666,
            0.20350162981252795
        ]
    },
    "11": {
        "position": [
            [
                3,
                2
            ],
            [
                4,
                4
            ],
            [
                3,
                0
            ]
        ],
        "values": 1.7484023466500265,
        "decision": [
            [
                [
                    0,
                    1
                ],
                [
                    0,
                    1
                ],
                [
                    0,
                    1
                ]
            ],
            [
                [
                    1,
                    0
                ],
                [
                    0,
                    -1
                ],
                [
                    0,
                    -1
                ]
            ],
            [
                [
                    1,
                    0
                ],
                [
                    0,
                    1
                ],
                [
                    1,
                    0
                ]
            ]
        ],
        "gain": [
            0.1941715390002171,
            0.27385089782118305,
            0.1842875556551959
        ]
    },
    "12": {
        "position": [
            [
                3,
                3
            ],
            [
                5,
                4
            ],
            [
                4,
                0
            ]
        ],
        "values": 1.5173480246947872,
        "decision": [
            [
                [
                    0,
                    1
                ],
                [
                    0,
                    1
                ],
                [
                    0,
                    0
                ]
            ],
            [
                [
                    0,
                    0
                ],
                [
                    0,
                    -1
                ],
                [
                    -1,
                    0
                ]
            ],
            [
                [
                    0,
                    1
                ],
                [
                    1,
                    0
                ],
                [
                    0,
                    1
                ]
            ]
        ],
        "gain": [
            0.12240353614869533,
            0.13692544891059152,
            0.24819017221209067
        ]
    },
    "13": {
        "position": [
            [
                3,
                4
            ],
            [
                5,
                4
            ],
            [
                4,
                1
            ]
        ],
        "values": 1.3221287675129398,
        "decision": [
            [
                [
                    0,
                    1
                ],
                [
                    0,
                    0
                ],
                [
                    0,
                    0
                ]
            ],
            [
                [
                    0,
                    -1
                ],
                [
                    -1,
                    0
                ],
                [
                    0,
                    1
                ]
            ],
            [
                [
                    0,
                    0
                ],
                [
                    1,
                    0
                ],
                [
                    0,
                    1
                ]
            ]
        ],
        "gain": [
            0.269171617038145,
            0.13818810384870733,
            0.12409508610604533
        ]
    },
    "14": {
        "position": [
            [
                3,
                5
            ],
            [
                5,
                3
            ],
            [
                4,
                1
            ]
        ],
        "values": 1.1627835354037581,
        "decision": [
            [
                [
                    -1,
                    0
                ],
                [
                    -1,
                    0
                ],
                [
                    -1,
                    0
                ]
            ],
            [
                [
                    0,
                    -1
                ],
                [
                    0,
                    -1
                ],
                [
                    0,
                    -1
                ]
            ],
            [
                [
                    -1,
                    0
                ],
                [
                    -1,
                    0
                ],
                [
                    0,
                    1
                ]
            ]
        ],
        "gain": [
            0.058519941737533165,
            0.180581827679949,
            0.12446685208312805
        ]
    },
    "15": {
        "position": [
            [
                2,
                5
            ],
            [
                5,
                2
            ],
            [
                3,
                1
            ]
        ],
        "values": 1.1234678115447334,
        "decision": [
            [
                [
                    -1,
                    0
                ],
                [
                    -1,
                    0
                ],
                [
                    0,
                    0
                ]
            ],
            [
                [
                    0,
                    -1
                ],
                [
                    0,
                    -1
                ],
                [
                    -1,
                    0
                ]
            ],
            [
                [
                    -1,
                    0
                ],
                [
                    0,
                    1
                ],
                [
                    -1,
                    0
                ]
            ]
        ],
        "gain": [
            0.10170764037987244,
            0.13755709724584322,
            0.10957001182585535
        ]
    },
    "16": {
        "position": [
            [
                1,
                5
            ],
            [
                5,
                1
            ],
            [
                2,
                1
            ]
        ],
        "values": 1.1545485601014849,
        "decision": [
            [
                [
                    -1,
                    0
                ],
                [
                    0,
                    0
                ],
                [
                    0,
                    0
                ]
            ],
            [
                [
                    0,
                    1
                ],
                [
                    0,
                    1
                ],
                [
                    -1,
                    0
                ]
            ],
            [
                [
                    -1,
                    0
                ],
                [
                    -1,
                    0
                ],
                [
                    0,
                    -1
                ]
            ]
        ],
        "gain": [
            0.23661644511151583,
            0.0902909138399745,
            0.00131537681314986
        ]
    },
    "17": {
        "position": [
            [
                0,
                5
            ],
            [
                5,
                2
            ],
            [
                1,
                1
            ]
        ],
        "values": 1.2953020822524661,
        "decision": [
            [
                [
                    0,
                    -1
                ],
                [
                    0,
                    -1
                ],
                [
                    0,
                    -1
                ]
            ],
            [
                [
                    0,
                    1
                ],
                [
                    -1,
                    0
                ],
                [
                    0,
                    1
                ]
            ],
            [
                [
                    0,
                    -1
                ],
                [
                    -1,
                    0
                ],
                [
                    0,
                    1
                ]
            ]
        ],
        "gain": [
            0.0385997288592107,
            0.06909405192435367,
            0.15344792276177546
        ]
    },
    "18": {
        "position": [
            [
                0,
                4
            ],
            [
                5,
                3
            ],
            [
                1,
                0
            ]
        ],
        "values": 1.349418903318654,
        "decision": [
            [
                [
                    0,
                    -1
                ],
                [
                    1,
                    0
                ],
                [
                    0,
                    -1
                ]
            ],
            [
                [
                    -1,
                    0
                ],
                [
                    -1,
                    0
                ],
                [
                    -1,
                    0
                ]
            ],
            [
                [
                    -1,
                    0
                ],
                [
                    0,
                    1
                ],
                [
                    0,
                    1
                ]
            ]
        ],
        "gain": [
            0.1307231807082383,
            0.1497444130916928,
            0.21619939675414662
        ]
    },
    "19": {
        "position": [
            [
                0,
                3
            ],
            [
                4,
                3
            ],
            [
                0,
                0
            ]
        ],
        "values": 1.2018030563785806,
        "decision": [
            [
                [
                    1,
                    0
                ],
                [
                    1,
                    0
                ],
                [
                    0,
                    1
                ]
            ],
            [
                [
                    0,
                    1
                ],
                [
                    -1,
                    0
                ],
                [
                    0,
                    1
                ]
            ],
            [
                [
                    0,
                    1
                ],
                [
                    0,
                    1
                ],
                [
                    1,
                    0
                ]
            ]
        ],
        "gain": [
            0.12310043440469443,
            0.12091190972394833,
            0.21382562873301475
        ]
    },
    "t": 389.12222051620483
}