{
    "gridmap": [
        [
            0.5017119571514081,
            0.5393354062064886,
            0.13587420195528843,
            0.306386568421659,
            0.5791846788017333,
            0.7912866394965615
        ],
        [
            0.15107398269944206,
            0.22916386669926614,
            0.9403500064849867,
            0.6661674958654504,
            0.764633787879766,
            0.659298910640315
        ],
        [
            0.2119863970193987,
            0.23054234744899116,
            0.22424658417666987,
            0.4818849686915082,
            0.5648396490529685,
            0.9760863665365014
        ],
        [
            0.7939457167905265,
            0.11831348351995141,
            0.8532614098361279,
            0.2773922127199193,
            0.25405001608064015,
            0.4144238269983431
        ],
        [
            0.7767585715600159,
            0.8045607491314318,
            0.7720217217792991,
            0.5110759181497846,
            0.17332570541930814,
            0.3825743218132568
        ],
        [
            0.6067087210923887,
            0.36159396181176984,
            0.23941143956267308,
            0.811792330128515,
            0.028726931410811507,
            0.556944605094959
        ]
    ],
    "0": {
        "position": [
            [
                1,
                1
            ],
            [
                2,
                2
            ],
            [
                3,
                3
            ]
        ],
        "values": 3.4119030776290202,
        "decision": [
            [
                [
                    0,
                    1
                ],
                [
                    0,
                    1
                ],
                [
                    0,
                    1
                ]
            ],
            [
                [
                    0,
                    1
                ],
                [
                    0,
                    1
                ],
                [
                    0,
                    1
                ]
            ],
            [
                [
                    0,
                    -1
                ],
                [
                    1,
                    0
                ],
                [
                    0,
                    -1
                ]
            ]
        ],
        "gain": [
            0.47017500324249334,
            0.2409424843457541,
            0.42663070491806393
        ]
    },
    "1": {
        "position": [
            [
                1,
                2
            ],
            [
                2,
                3
            ],
            [
                3,
                2
            ]
        ],
        "values": 3.2817759656237406,
        "decision": [
            [
                [
                    0,
                    1
                ],
                [
                    0,
                    1
                ],
                [
                    -1,
                    0
                ]
            ],
            [
                [
                    0,
                    1
                ],
                [
                    0,
                    1
                ],
                [
                    -1,
                    0
                ]
            ],
            [
                [
                    1,
                    0
                ],
                [
                    0,
                    -1
                ],
                [
                    0,
                    -1
                ]
            ]
        ],
        "gain": [
            0.3330837479327252,
            0.28241982452648423,
            0.38601086088964953
        ]
    },
    "2": {
        "position": [
            [
                1,
                3
            ],
            [
                2,
                4
            ],
            [
                4,
                2
            ]
        ],
        "values": 3.3168993020525512,
        "decision": [
            [
                [
                    0,
                    1
                ],
                [
                    -1,
                    0
                ],
                [
                    0,
                    1
                ]
            ],
            [
                [
                    0,
                    1
                ],
                [
                    -1,
                    0
                ],
                [
                    1,
                    0
                ]
            ],
            [
                [
                    0,
                    -1
                ],
                [
                    0,
                    -1
                ],
                [
                    -1,
                    0
                ]
            ]
        ],
        "gain": [
            0.382316893939883,
            0.4880431832682507,
            0.4022803745657159
        ]
    },
    "3": {
        "position": [
            [
                1,
                4
            ],
            [
                2,
                5
            ],
            [
                4,
                1
            ]
        ],
        "values": 2.6783488228807135,
        "decision": [
            [
                [
                    0,
                    1
                ],
                [
                    -1,
                    0
                ],
                [
                    0,
                    -1
                ]
            ],
            [
                [
                    1,
                    0
                ],
                [
                    1,
                    0
                ],
                [
                    1,
                    0
                ]
            ],
            [
                [
                    0,
                    0
                ],
                [
                    0,
                    -1
                ],
                [
                    -1,
                    0
                ]
            ]
        ],
        "gain": [
            0.3296494553201575,
            0.20721191349917156,
            0.20114018728285796
        ]
    },
    "4": {
        "position": [
            [
                1,
                5
            ],
            [
                3,
                5
            ],
            [
                4,
                1
            ]
        ],
        "values": 2.475891507124038,
        "decision": [
            [
                [
                    -1,
                    0
                ],
                [
                    0,
                    -1
                ],
                [
                    0,
                    1
                ]
            ],
            [
                [
                    1,
                    0
                ],
                [
                    1,
                    0
                ],
                [
                    0,
                    0
                ]
            ],
            [
                [
                    0,
                    -1
                ],
                [
                    -1,
                    0
                ],
                [
                    0,
                    0
                ]
            ]
        ],
        "gain": [
            0.39564331974828076,
            0.1912871609066284,
            0.38837928578000797
        ]
    },
    "5": {
        "position": [
            [
                0,
                5
            ],
            [
                4,
                5
            ],
            [
                4,
                0
            ]
        ],
        "values": 2.321186284925214,
        "decision": [
            [
                [
                    0,
                    0
                ],
                [
                    0,
                    -1
                ],
                [
                    1,
                    0
                ]
            ],
            [
                [
                    0,
                    -1
                ],
                [
                    0,
                    -1
                ],
                [
                    1,
                    0
                ]
            ],
            [
                [
                    1,
                    0
                ],
                [
                    -1,
                    0
                ],
                [
                    -1,
                    0
                ]
            ]
        ],
        "gain": [
            0.19782165987414038,
            0.08666285270965407,
            0.30335436054619436
        ]
    },
    "6": {
        "position": [
            [
                0,
                5
            ],
            [
                4,
                4
            ],
            [
                5,
                0
            ]
        ],
        "values": 2.301323797491348,
        "decision": [
            [
                [
                    0,
                    -1
                ],
                [
                    1,
                    0
                ],
                [
                    0,
                    -1
                ]
            ],
            [
                [
                    0,
                    -1
                ],
                [
                    1,
                    0
                ],
                [
                    0,
                    0
                ]
            ],
            [
                [
                    -1,
                    0
                ],
                [
                    -1,
                    0
                ],
                [
                    0,
                    0
                ]
            ]
        ],
        "gain": [
            0.28959233940086665,
            0.2555379590748923,
            0.19418964289000398
        ]
    },
    "7": {
        "position": [
            [
                0,
                4
            ],
            [
                4,
                3
            ],
            [
                4,
                0
            ]
        ],
        "values": 2.0380704795005724,
        "decision": [
            [
                [
                    1,
                    0
                ],
                [
                    0,
                    1
                ],
                [
                    1,
                    0
                ]
            ],
            [
                [
                    1,
                    0
                ],
                [
                    0,
                    0
                ],
                [
                    -1,
                    0
                ]
            ],
            [
                [
                    -1,
                    0
                ],
                [
                    -1,
                    0
                ],
                [
                    1,
                    0
                ]
            ]
        ],
        "gain": [
            0.1911584469699415,
            0.4058961650642575,
            0.39697285839526325
        ]
    },
    "8": {
        "position": [
            [
                1,
                4
            ],
            [
                5,
                3
            ],
            [
                3,
                0
            ]
        ],
        "values": 1.5447372474884853,
        "decision": [
            [
                [
                    0,
                    1
                ],
                [
                    1,
                    0
                ],
                [
                    0,
                    -1
                ]
            ],
            [
                [
                    0,
                    0
                ],
                [
                    -1,
                    0
                ],
                [
                    0,
                    -1
                ]
            ],
            [
                [
                    0,
                    0
                ],
                [
                    0,
                    1
                ],
                [
                    0,
                    1
                ]
            ]
        ],
        "gain": [
            0.16482472766007875,
            0.20294808253212876,
            0.19848642919763163
        ]
    },
    "9": {
        "position": [
            [
                1,
                5
            ],
            [
                5,
                3
            ],
            [
                3,
                0
            ]
        ],
        "values": 1.4787324428141149,
        "decision": [
            [
                [
                    1,
                    0
                ],
                [
                    0,
                    -1
                ],
                [
                    1,
                    0
                ]
            ],
            [
                [
                    -1,
                    0
                ],
                [
                    0,
                    -1
                ],
                [
                    -1,
                    0
                ]
            ],
            [
                [
                    -1,
                    0
                ],
                [
                    -1,
                    0
                ],
                [
                    -1,
                    0
                ]
            ]
        ],
        "gain": [
            0.24402159163412535,
            0.12776897953744615,
            0.10599319850969935
        ]
    },
    "10": {
        "position": [
            [
                2,
                5
            ],
            [
                4,
                3
            ],
            [
                2,
                0
            ]
        ],
        "values": 1.618799402042865,
        "decision": [
            [
                [
                    1,
                    0
                ],
                [
                    1,
                    0
                ],
                [
                    1,
                    0
                ]
            ],
            [
                [
                    0,
                    -1
                ],
                [
                    -1,
                    0
                ],
                [
                    0,
                    1
                ]
            ],
            [
                [
                    -1,
                    0
                ],
                [
                    -1,
                    0
                ],
                [
                    0,
                    1
                ]
            ]
        ],
        "gain": [
            0.10360595674958578,
            0.19300543044482477,
            0.07553699134972103
        ]
    },
    "11": {
        "position": [
            [
                3,
                5
            ],
            [
                4,
                2
            ],
            [
                1,
                0
            ]
        ],
        "values": 1.7292357136737175,
        "decision": [
            [
                [
                    1,
                    0
                ],
                [
                    1,
                    0
                ],
                [
                    0,
                    0
                ]
            ],
            [
                [
                    -1,
                    0
                ],
                [
                    -1,
                    0
                ],
                [
                    -1,
                    0
                ]
            ],
            [
                [
                    -1,
                    0
                ],
                [
                    0,
                    1
                ],
                [
                    0,
                    0
                ]
            ]
        ],
        "gain": [
            0.0956435804533142,
            0.21331535245903196,
            0.2508559785757041
        ]
    },
    "12": {
        "position": [
            [
                4,
                5
            ],
            [
                3,
                2
            ],
            [
                0,
                0
            ]
        ],
        "values": 1.5323728900314126,
        "decision": [
            [
                [
                    1,
                    0
                ],
                [
                    0,
                    0
                ],
                [
                    0,
                    0
                ]
            ],
            [
                [
                    0,
                    1
                ],
                [
                    -1,
                    0
                ],
                [
                    -1,
                    0
                ]
            ],
            [
                [
                    0,
                    1
                ],
                [
                    1,
                    0
                ],
                [
                    0,
                    1
                ]
            ]
        ],
        "gain": [
            0.2784723025474795,
            0.13869610635995966,
            0.2696677031032443
        ]
    },
    "13": {
        "position": [
            [
                5,
                5
            ],
            [
                3,
                3
            ],
            [
                0,
                1
            ]
        ],
        "values": 1.181385704009838,
        "decision": [
            [
                [
                    0,
                    0
                ],
                [
                    -1,
                    0
                ],
                [
                    1,
                    0
                ]
            ],
            [
                [
                    -1,
                    0
                ],
                [
                    -1,
                    0
                ],
                [
                    -1,
                    0
                ]
            ],
            [
                [
                    0,
                    0
                ],
                [
                    1,
                    0
                ],
                [
                    0,
                    1
                ]
            ]
        ],
        "gain": [
            0.13923615127373976,
            0.12047124217287705,
            0.13483385155162214
        ]
    },
    "14": {
        "position": [
            [
                5,
                5
            ],
            [
                2,
                3
            ],
            [
                0,
                1
            ]
        ],
        "values": 1.1672877404119353,
        "decision": [
            [
                [
                    0,
                    -1
                ],
                [
                    0,
                    -1
                ],
                [
                    0,
                    -1
                ]
            ],
            [
                [
                    -1,
                    0
                ],
                [
                    -1,
                    0
                ],
                [
                    0,
                    1
                ]
            ],
            [
                [
                    1,
                    0
                ],
                [
                    0,
                    1
                ],
                [
                    0,
                    0
                ]
            ]
        ],
        "gain": [
            0.014363465705405754,
            0.1665418739663626,
            0.11458193334963307
        ]
    },
    "15": {
        "position": [
            [
                5,
                4
            ],
            [
                1,
                3
            ],
            [
                1,
                1
            ]
        ],
        "values": 1.2636315703218237,
        "decision": [
            [
                [
                    0,
                    -1
                ],
                [
                    0,
                    -1
                ],
                [
                    0,
                    -1
                ]
            ],
            [
                [
                    -1,
                    0
                ],
                [
                    0,
                    1
                ],
                [
                    0,
                    1
                ]
            ],
            [
                [
                    0,
                    1
                ],
                [
                    1,
                    0
                ],
                [
                    -1,
                    0
                ]
            ]
        ],
        "gain": [
            0.10147404126606438,
            0.1531932842108295,
            0.23508750162124667
        ]
    },
    "16": {
        "position": [
            [
                5,
                3
            ],
            [
                0,
                3
            ],
            [
                1,
                2
            ]
        ],
        "values": 1.1787034030324186,
        "decision": [
            [
                [
                    0,
                    -1
                ],
                [
                    0,
                    -1
                ],
                [
                    0,
                    -1
                ]
            ],
            [
                [
                    0,
                    1
                ],
                [
                    1,
                    0
                ],
                [
                    1,
                    0
                ]
            ],
            [
                [
                    0,
                    0
                ],
                [
                    1,
                    0
                ],
                [
                    0,
                    -1
                ]
            ]
        ],
        "gain": [
            0.11970571978133654,
            0.14479616970043332,
            0.11754375081062333
        ]
    },
    "17": {
        "position": [
            [
                5,
                2
            ],
            [
                0,
                4
            ],
            [
                1,
                2
            ]
        ],
        "values": 1.1086668099527803,
        "decision": [
            [
                [
                    0,
                    -1
                ],
                [
                    0,
                    -1
                ],
                [
                    -1,
                    0
                ]
            ],
            [
                [
                    1,
                    0
                ],
                [
                    1,
                    0
                ],
                [
                    1,
                    0
                ]
            ],
            [
                [
                    1,
                    0
                ],
                [
                    1,
                    0
                ],
                [
                    1,
                    0
                ]
            ]
        ],
        "gain": [
            0.18079698090588492,
            0.09557922348497075,
            0.11212329208833494
        ]
    },
    "18": {
        "position": [
            [
                5,
                1
            ],
            [
                1,
                4
            ],
            [
                2,
                2
            ]
        ],
        "values": 0.9980059047196883,
        "decision": [
            [
                [
                    0,
                    -1
                ],
                [
                    -1,
                    0
                ],
                [
                    0,
                    1
                ]
            ],
            [
                [
                    0,
                    1
                ],
                [
                    1,
                    0
                ],
                [
                    0,
                    -1
                ]
            ],
            [
                [
                    1,
                    0
                ],
                [
                    0,
                    1
                ],
                [
                    0,
                    1
                ]
            ]
        ],
        "gain": [
            0.15167718027309718,
            0.08241236383003937,
            0.10665767622951598
        ]
    },
    "19": {
        "position": [
            [
                5,
                0
            ],
            [
                1,
                5
            ],
            [
                3,
                2
            ]
        ],
        "values": 0.949893641617775,
        "decision": [
            [
                [
                    0,
                    0
                ],
                [
                    -1,
                    0
                ],
                [
                    -1,
                    0
                ]
            ],
            [
                [
                    1,
                    0
                ],
                [
                    0,
                    -1
                ],
                [
                    1,
                    0
                ]
            ],
            [
                [
                    1,
                    0
                ],
                [
                    0,
                    -1
                ],
                [
                    1,
                    0
                ]
            ]
        ],
        "gain": [
            0.07583859013654859,
            0.12201079581706267,
            0.09650271522241238
        ]
    },
    "t": 369.46142053604126
}