{
    "gridmap": [
        [
            0.8943782684389072,
            0.5207209501819198,
            0.6764041394632979,
            0.6691989381260477,
            0.564838089765307,
            0.5245346994047532
        ],
        [
            0.003972654778709672,
            0.7483755166111346,
            0.9689979652115958,
            0.7780610986420139,
            0.5144959845408813,
            0.9620187104932029
        ],
        [
            0.6166875455130613,
            0.9769404994876412,
            0.7890523598368528,
            0.019879363914613202,
            0.15253372347401883,
            0.901422554053446
        ],
        [
            0.10101534506725784,
            0.20276463894173402,
            0.2572703090122551,
            0.35575019160244037,
            0.3911927812947389,
            0.4452775909590827
        ],
        [
            0.536447975355793,
            0.5111586687416732,
            0.2231651720090253,
            0.8286060020265803,
            0.6178514277866662,
            0.31257542314355513
        ],
        [
            0.1327097992921894,
            0.9536373983023242,
            0.9269779791394923,
            0.5546630141763794,
            0.5627739876006722,
            0.9809605220513997
        ]
    ],
    "0": {
        "values": [
            3.0091035261140804,
            3.3206544081031013,
            2.522618909939271
        ],
        "policyset": [
            [
                [
                    [
                        0,
                        1
                    ],
                    [
                        1,
                        0
                    ],
                    [
                        0,
                        -1
                    ]
                ],
                [
                    [
                        0,
                        -1
                    ],
                    [
                        0,
                        1
                    ],
                    [
                        -1,
                        0
                    ]
                ],
                [
                    [
                        1,
                        0
                    ],
                    [
                        1,
                        0
                    ],
                    [
                        0,
                        -1
                    ]
                ]
            ],
            [
                [
                    [
                        0,
                        0
                    ],
                    [
                        0,
                        1
                    ],
                    [
                        0,
                        1
                    ]
                ],
                [
                    [
                        0,
                        -1
                    ],
                    [
                        -1,
                        0
                    ],
                    [
                        0,
                        1
                    ]
                ],
                [
                    [
                        1,
                        0
                    ],
                    [
                        1,
                        0
                    ],
                    [
                        0,
                        -1
                    ]
                ]
            ],
            [
                [
                    [
                        0,
                        1
                    ],
                    [
                        1,
                        0
                    ],
                    [
                        0,
                        -1
                    ]
                ],
                [
                    [
                        -1,
                        0
                    ],
                    [
                        1,
                        0
                    ],
                    [
                        0,
                        -1
                    ]
                ],
                [
                    [
                        1,
                        0
                    ],
                    [
                        1,
                        0
                    ],
                    [
                        0,
                        -1
                    ]
                ]
            ]
        ],
        "converge": -1,
        "position": [
            [
                1,
                1
            ],
            [
                2,
                2
            ],
            [
                3,
                3
            ]
        ],
        "decision": [
            [
                [
                    0,
                    0
                ],
                [
                    0,
                    1
                ],
                [
                    0,
                    1
                ]
            ],
            [
                [
                    0,
                    -1
                ],
                [
                    -1,
                    0
                ],
                [
                    0,
                    1
                ]
            ],
            [
                [
                    1,
                    0
                ],
                [
                    1,
                    0
                ],
                [
                    0,
                    -1
                ]
            ]
        ],
        "gain": [
            0.3741877583055673,
            0.4884702497438206,
            0.41430300101329015
        ]
    },
    "1": {
        "values": [
            3.257059142680755,
            3.4007459377519007
        ],
        "policyset": [
            [
                [
                    [
                        0,
                        1
                    ],
                    [
                        0,
                        1
                    ],
                    [
                        -1,
                        0
                    ]
                ],
                [
                    [
                        0,
                        1
                    ],
                    [
                        -1,
                        0
                    ],
                    [
                        0,
                        1
                    ]
                ],
                [
                    [
                        1,
                        0
                    ],
                    [
                        0,
                        -1
                    ],
                    [
                        0,
                        -1
                    ]
                ]
            ],
            [
                [
                    [
                        0,
                        1
                    ],
                    [
                        0,
                        1
                    ],
                    [
                        -1,
                        0
                    ]
                ],
                [
                    [
                        0,
                        1
                    ],
                    [
                        -1,
                        0
                    ],
                    [
                        -1,
                        0
                    ]
                ],
                [
                    [
                        1,
                        0
                    ],
                    [
                        0,
                        -1
                    ],
                    [
                        0,
                        -1
                    ]
                ]
            ]
        ],
        "converge": 1,
        "position": [
            [
                1,
                1
            ],
            [
                2,
                1
            ],
            [
                4,
                3
            ]
        ],
        "decision": [
            [
                [
                    0,
                    1
                ],
                [
                    0,
                    1
                ],
                [
                    -1,
                    0
                ]
            ],
            [
                [
                    0,
                    1
                ],
                [
                    -1,
                    0
                ],
                [
                    -1,
                    0
                ]
            ],
            [
                [
                    1,
                    0
                ],
                [
                    0,
                    -1
                ],
                [
                    0,
                    -1
                ]
            ]
        ],
        "gain": [
            0.4844989826057979,
            0.3945261799184264,
            0.2773315070881897
        ]
    },
    "2": {
        "values": [
            3.09453915495622,
            3.22105596523211
        ],
        "policyset": [
            [
                [
                    [
                        0,
                        1
                    ],
                    [
                        0,
                        1
                    ],
                    [
                        0,
                        1
                    ]
                ],
                [
                    [
                        -1,
                        0
                    ],
                    [
                        0,
                        1
                    ],
                    [
                        -1,
                        0
                    ]
                ],
                [
                    [
                        0,
                        -1
                    ],
                    [
                        0,
                        -1
                    ],
                    [
                        -1,
                        0
                    ]
                ]
            ],
            [
                [
                    [
                        0,
                        1
                    ],
                    [
                        0,
                        1
                    ],
                    [
                        0,
                        1
                    ]
                ],
                [
                    [
                        -1,
                        0
                    ],
                    [
                        -1,
                        0
                    ],
                    [
                        0,
                        1
                    ]
                ],
                [
                    [
                        0,
                        -1
                    ],
                    [
                        0,
                        -1
                    ],
                    [
                        0,
                        0
                    ]
                ]
            ]
        ],
        "converge": 1,
        "position": [
            [
                1,
                2
            ],
            [
                2,
                2
            ],
            [
                5,
                3
            ]
        ],
        "decision": [
            [
                [
                    0,
                    1
                ],
                [
                    0,
                    1
                ],
                [
                    0,
                    1
                ]
            ],
            [
                [
                    -1,
                    0
                ],
                [
                    -1,
                    0
                ],
                [
                    0,
                    1
                ]
            ],
            [
                [
                    0,
                    -1
                ],
                [
                    0,
                    -1
                ],
                [
                    0,
                    0
                ]
            ]
        ],
        "gain": [
            0.38903054932100695,
            0.24224949130289894,
            0.46348898956974616
        ]
    },
    "3": {
        "values": [
            3.235342324785723,
            3.069153027100361
        ],
        "policyset": [
            [
                [
                    [
                        0,
                        1
                    ],
                    [
                        0,
                        1
                    ],
                    [
                        1,
                        0
                    ]
                ],
                [
                    [
                        -1,
                        0
                    ],
                    [
                        0,
                        -1
                    ],
                    [
                        0,
                        -1
                    ]
                ],
                [
                    [
                        0,
                        -1
                    ],
                    [
                        -1,
                        0
                    ],
                    [
                        0,
                        -1
                    ]
                ]
            ],
            [
                [
                    [
                        0,
                        1
                    ],
                    [
                        0,
                        1
                    ],
                    [
                        1,
                        0
                    ]
                ],
                [
                    [
                        -1,
                        0
                    ],
                    [
                        0,
                        -1
                    ],
                    [
                        0,
                        -1
                    ]
                ],
                [
                    [
                        0,
                        -1
                    ],
                    [
                        0,
                        0
                    ],
                    [
                        0,
                        0
                    ]
                ]
            ]
        ],
        "converge": 1,
        "position": [
            [
                1,
                3
            ],
            [
                1,
                2
            ],
            [
                5,
                2
            ]
        ],
        "decision": [
            [
                [
                    0,
                    1
                ],
                [
                    0,
                    1
                ],
                [
                    1,
                    0
                ]
            ],
            [
                [
                    -1,
                    0
                ],
                [
                    0,
                    -1
                ],
                [
                    0,
                    -1
                ]
            ],
            [
                [
                    0,
                    -1
                ],
                [
                    0,
                    0
                ],
                [
                    0,
                    0
                ]
            ]
        ],
        "gain": [
            0.25724799227044065,
            0.33820206973164896,
            0.4768186991511621
        ]
    },
    "4": {
        "values": [
            2.8655821579410796
        ],
        "policyset": [
            [
                [
                    [
                        0,
                        1
                    ],
                    [
                        1,
                        0
                    ],
                    [
                        -1,
                        0
                    ]
                ],
                [
                    [
                        0,
                        -1
                    ],
                    [
                        0,
                        -1
                    ],
                    [
                        0,
                        0
                    ]
                ],
                [
                    [
                        0,
                        0
                    ],
                    [
                        -1,
                        0
                    ],
                    [
                        0,
                        -1
                    ]
                ]
            ]
        ],
        "converge": 0,
        "position": [
            [
                1,
                4
            ],
            [
                0,
                2
            ],
            [
                5,
                1
            ]
        ],
        "decision": [
            [
                [
                    0,
                    1
                ],
                [
                    1,
                    0
                ],
                [
                    -1,
                    0
                ]
            ],
            [
                [
                    0,
                    -1
                ],
                [
                    0,
                    -1
                ],
                [
                    0,
                    0
                ]
            ],
            [
                [
                    0,
                    0
                ],
                [
                    -1,
                    0
                ],
                [
                    0,
                    -1
                ]
            ]
        ],
        "gain": [
            0.48100935524660143,
            0.2603604750909599,
            0.23840934957558105
        ]
    },
    "5": {
        "values": [
            2.412362559114742,
            2.2292410355684904
        ],
        "policyset": [
            [
                [
                    [
                        1,
                        0
                    ],
                    [
                        -1,
                        0
                    ],
                    [
                        -1,
                        0
                    ]
                ],
                [
                    [
                        0,
                        -1
                    ],
                    [
                        0,
                        1
                    ],
                    [
                        0,
                        -1
                    ]
                ],
                [
                    [
                        -1,
                        0
                    ],
                    [
                        0,
                        -1
                    ],
                    [
                        0,
                        0
                    ]
                ]
            ],
            [
                [
                    [
                        1,
                        0
                    ],
                    [
                        0,
                        0
                    ],
                    [
                        0,
                        0
                    ]
                ],
                [
                    [
                        0,
                        -1
                    ],
                    [
                        0,
                        0
                    ],
                    [
                        0,
                        0
                    ]
                ],
                [
                    [
                        -1,
                        0
                    ],
                    [
                        0,
                        -1
                    ],
                    [
                        0,
                        0
                    ]
                ]
            ]
        ],
        "converge": 1,
        "position": [
            [
                1,
                5
            ],
            [
                0,
                1
            ],
            [
                5,
                1
            ]
        ],
        "decision": [
            [
                [
                    1,
                    0
                ],
                [
                    0,
                    0
                ],
                [
                    0,
                    0
                ]
            ],
            [
                [
                    0,
                    -1
                ],
                [
                    0,
                    0
                ],
                [
                    0,
                    0
                ]
            ],
            [
                [
                    -1,
                    0
                ],
                [
                    0,
                    -1
                ],
                [
                    0,
                    0
                ]
            ]
        ],
        "gain": [
            0.450711277026723,
            0.4471891342194536,
            0.2555793343708366
        ]
    },
    "6": {
        "values": [
            2.1572487266506553
        ],
        "policyset": [
            [
                [
                    [
                        1,
                        0
                    ],
                    [
                        1,
                        0
                    ],
                    [
                        1,
                        0
                    ]
                ],
                [
                    [
                        0,
                        1
                    ],
                    [
                        0,
                        1
                    ],
                    [
                        0,
                        1
                    ]
                ],
                [
                    [
                        -1,
                        0
                    ],
                    [
                        -1,
                        0
                    ],
                    [
                        0,
                        -1
                    ]
                ]
            ]
        ],
        "converge": 0,
        "position": [
            [
                2,
                5
            ],
            [
                0,
                0
            ],
            [
                4,
                1
            ]
        ],
        "decision": [
            [
                [
                    1,
                    0
                ],
                [
                    1,
                    0
                ],
                [
                    1,
                    0
                ]
            ],
            [
                [
                    0,
                    1
                ],
                [
                    0,
                    1
                ],
                [
                    0,
                    1
                ]
            ],
            [
                [
                    -1,
                    0
                ],
                [
                    -1,
                    0
                ],
                [
                    0,
                    -1
                ]
            ]
        ],
        "gain": [
            0.22263879547954135,
            0.13018023754547994,
            0.10138231947086701
        ]
    },
    "7": {
        "values": [
            2.4210252992160215,
            2.3848784359285355
        ],
        "policyset": [
            [
                [
                    [
                        1,
                        0
                    ],
                    [
                        1,
                        0
                    ],
                    [
                        0,
                        -1
                    ]
                ],
                [
                    [
                        0,
                        1
                    ],
                    [
                        0,
                        1
                    ],
                    [
                        0,
                        1
                    ]
                ],
                [
                    [
                        -1,
                        0
                    ],
                    [
                        0,
                        -1
                    ],
                    [
                        0,
                        0
                    ]
                ]
            ],
            [
                [
                    [
                        1,
                        0
                    ],
                    [
                        1,
                        0
                    ],
                    [
                        0,
                        0
                    ]
                ],
                [
                    [
                        0,
                        1
                    ],
                    [
                        0,
                        1
                    ],
                    [
                        0,
                        1
                    ]
                ],
                [
                    [
                        -1,
                        0
                    ],
                    [
                        0,
                        -1
                    ],
                    [
                        0,
                        0
                    ]
                ]
            ]
        ],
        "converge": 1,
        "position": [
            [
                3,
                5
            ],
            [
                0,
                1
            ],
            [
                3,
                1
            ]
        ],
        "decision": [
            [
                [
                    1,
                    0
                ],
                [
                    1,
                    0
                ],
                [
                    0,
                    0
                ]
            ],
            [
                [
                    0,
                    1
                ],
                [
                    0,
                    1
                ],
                [
                    0,
                    1
                ]
            ],
            [
                [
                    -1,
                    0
                ],
                [
                    0,
                    -1
                ],
                [
                    0,
                    0
                ]
            ]
        ],
        "gain": [
            0.15628771157177757,
            0.16910103486582448,
            0.2442351248719103
        ]
    },
    "8": {
        "values": [
            2.587803257519122,
            2.4359948513108685,
            2.4359948513108685
        ],
        "policyset": [
            [
                [
                    [
                        1,
                        0
                    ],
                    [
                        0,
                        -1
                    ],
                    [
                        -1,
                        0
                    ]
                ],
                [
                    [
                        0,
                        1
                    ],
                    [
                        0,
                        1
                    ],
                    [
                        0,
                        1
                    ]
                ],
                [
                    [
                        0,
                        1
                    ],
                    [
                        0,
                        -1
                    ],
                    [
                        0,
                        -1
                    ]
                ]
            ],
            [
                [
                    [
                        1,
                        0
                    ],
                    [
                        0,
                        0
                    ],
                    [
                        0,
                        -1
                    ]
                ],
                [
                    [
                        0,
                        1
                    ],
                    [
                        0,
                        1
                    ],
                    [
                        0,
                        1
                    ]
                ],
                [
                    [
                        0,
                        -1
                    ],
                    [
                        0,
                        0
                    ],
                    [
                        0,
                        0
                    ]
                ]
            ],
            [
                [
                    [
                        1,
                        0
                    ],
                    [
                        0,
                        -1
                    ],
                    [
                        0,
                        1
                    ]
                ],
                [
                    [
                        0,
                        1
                    ],
                    [
                        0,
                        1
                    ],
                    [
                        0,
                        1
                    ]
                ],
                [
                    [
                        0,
                        -1
                    ],
                    [
                        0,
                        0
                    ],
                    [
                        0,
                        0
                    ]
                ]
            ]
        ],
        "converge": -1,
        "position": [
            [
                4,
                5
            ],
            [
                0,
                2
            ],
            [
                2,
                1
            ]
        ],
        "decision": [
            [
                [
                    1,
                    0
                ],
                [
                    0,
                    -1
                ],
                [
                    -1,
                    0
                ]
            ],
            [
                [
                    0,
                    1
                ],
                [
                    0,
                    1
                ],
                [
                    0,
                    1
                ]
            ],
            [
                [
                    0,
                    1
                ],
                [
                    0,
                    -1
                ],
                [
                    0,
                    -1
                ]
            ]
        ],
        "gain": [
            0.49048026102569986,
            0.33459946906302385,
            0.1972630899592132
        ]
    },
    "9": {
        "values": [
            2.205377131985601
        ],
        "policyset": [
            [
                [
                    [
                        0,
                        0
                    ],
                    [
                        0,
                        -1
                    ],
                    [
                        -1,
                        0
                    ]
                ],
                [
                    [
                        0,
                        1
                    ],
                    [
                        0,
                        1
                    ],
                    [
                        1,
                        0
                    ]
                ],
                [
                    [
                        0,
                        -1
                    ],
                    [
                        0,
                        -1
                    ],
                    [
                        0,
                        0
                    ]
                ]
            ]
        ],
        "converge": 0,
        "position": [
            [
                5,
                5
            ],
            [
                0,
                3
            ],
            [
                2,
                2
            ]
        ],
        "decision": [
            [
                [
                    0,
                    0
                ],
                [
                    0,
                    -1
                ],
                [
                    -1,
                    0
                ]
            ],
            [
                [
                    0,
                    1
                ],
                [
                    0,
                    1
                ],
                [
                    1,
                    0
                ]
            ],
            [
                [
                    0,
                    -1
                ],
                [
                    0,
                    -1
                ],
                [
                    0,
                    0
                ]
            ]
        ],
        "gain": [
            0.24524013051284993,
            0.2824190448826535,
            0.12211756243595515
        ]
    },
    "10": {
        "values": [
            2.152667307007409,
            2.012504832803303
        ],
        "policyset": [
            [
                [
                    [
                        0,
                        -1
                    ],
                    [
                        -1,
                        0
                    ],
                    [
                        0,
                        -1
                    ]
                ],
                [
                    [
                        0,
                        1
                    ],
                    [
                        1,
                        0
                    ],
                    [
                        1,
                        0
                    ]
                ],
                [
                    [
                        0,
                        -1
                    ],
                    [
                        1,
                        0
                    ],
                    [
                        1,
                        0
                    ]
                ]
            ],
            [
                [
                    [
                        0,
                        -1
                    ],
                    [
                        -1,
                        0
                    ],
                    [
                        0,
                        0
                    ]
                ],
                [
                    [
                        0,
                        1
                    ],
                    [
                        1,
                        0
                    ],
                    [
                        1,
                        0
                    ]
                ],
                [
                    [
                        0,
                        -1
                    ],
                    [
                        0,
                        0
                    ],
                    [
                        0,
                        0
                    ]
                ]
            ]
        ],
        "converge": 1,
        "position": [
            [
                5,
                5
            ],
            [
                0,
                4
            ],
            [
                2,
                1
            ]
        ],
        "decision": [
            [
                [
                    0,
                    -1
                ],
                [
                    -1,
                    0
                ],
                [
                    0,
                    0
                ]
            ],
            [
                [
                    0,
                    1
                ],
                [
                    1,
                    0
                ],
                [
                    1,
                    0
                ]
            ],
            [
                [
                    0,
                    -1
                ],
                [
                    0,
                    0
                ],
                [
                    0,
                    0
                ]
            ]
        ],
        "gain": [
            0.2813869938003361,
            0.2622673497023766,
            0.30834377275653063
        ]
    },
    "11": {
        "values": [
            1.7638498477788398,
            1.7094963803454308
        ],
        "policyset": [
            [
                [
                    [
                        -1,
                        0
                    ],
                    [
                        0,
                        -1
                    ],
                    [
                        -1,
                        0
                    ]
                ],
                [
                    [
                        0,
                        0
                    ],
                    [
                        1,
                        0
                    ],
                    [
                        1,
                        0
                    ]
                ],
                [
                    [
                        0,
                        0
                    ],
                    [
                        1,
                        0
                    ],
                    [
                        1,
                        0
                    ]
                ]
            ],
            [
                [
                    [
                        -1,
                        0
                    ],
                    [
                        0,
                        -1
                    ],
                    [
                        0,
                        1
                    ]
                ],
                [
                    [
                        1,
                        0
                    ],
                    [
                        1,
                        0
                    ],
                    [
                        -1,
                        0
                    ]
                ],
                [
                    [
                        1,
                        0
                    ],
                    [
                        1,
                        0
                    ],
                    [
                        0,
                        0
                    ]
                ]
            ]
        ],
        "converge": 1,
        "position": [
            [
                5,
                4
            ],
            [
                0,
                5
            ],
            [
                2,
                0
            ]
        ],
        "decision": [
            [
                [
                    -1,
                    0
                ],
                [
                    0,
                    -1
                ],
                [
                    0,
                    1
                ]
            ],
            [
                [
                    1,
                    0
                ],
                [
                    1,
                    0
                ],
                [
                    -1,
                    0
                ]
            ],
            [
                [
                    1,
                    0
                ],
                [
                    1,
                    0
                ],
                [
                    0,
                    0
                ]
            ]
        ],
        "gain": [
            0.3089257138933331,
            0.24050467762330072,
            0.05050767253362892
        ]
    },
    "12": {
        "values": [
            1.44742367191063,
            1.4413260946703146,
            1.386690001644686
        ],
        "policyset": [
            [
                [
                    [
                        0,
                        -1
                    ],
                    [
                        -1,
                        0
                    ],
                    [
                        0,
                        1
                    ]
                ],
                [
                    [
                        1,
                        0
                    ],
                    [
                        1,
                        0
                    ],
                    [
                        0,
                        -1
                    ]
                ],
                [
                    [
                        1,
                        0
                    ],
                    [
                        0,
                        1
                    ],
                    [
                        0,
                        -1
                    ]
                ]
            ],
            [
                [
                    [
                        0,
                        -1
                    ],
                    [
                        1,
                        0
                    ],
                    [
                        0,
                        -1
                    ]
                ],
                [
                    [
                        1,
                        0
                    ],
                    [
                        0,
                        0
                    ],
                    [
                        0,
                        0
                    ]
                ],
                [
                    [
                        1,
                        0
                    ],
                    [
                        0,
                        0
                    ],
                    [
                        0,
                        0
                    ]
                ]
            ],
            [
                [
                    [
                        0,
                        -1
                    ],
                    [
                        -1,
                        0
                    ],
                    [
                        0,
                        1
                    ]
                ],
                [
                    [
                        1,
                        0
                    ],
                    [
                        1,
                        0
                    ],
                    [
                        0,
                        -1
                    ]
                ],
                [
                    [
                        1,
                        0
                    ],
                    [
                        0,
                        0
                    ],
                    [
                        0,
                        0
                    ]
                ]
            ]
        ],
        "converge": -1,
        "position": [
            [
                4,
                4
            ],
            [
                1,
                5
            ],
            [
                3,
                0
            ]
        ],
        "decision": [
            [
                [
                    0,
                    -1
                ],
                [
                    -1,
                    0
                ],
                [
                    0,
                    1
                ]
            ],
            [
                [
                    1,
                    0
                ],
                [
                    1,
                    0
                ],
                [
                    0,
                    -1
                ]
            ],
            [
                [
                    1,
                    0
                ],
                [
                    0,
                    1
                ],
                [
                    0,
                    -1
                ]
            ]
        ],
        "gain": [
            0.20715150050664508,
            0.2253556385133615,
            0.2682239876778965
        ]
    },
    "13": {
        "values": [
            1.1179925778931088,
            1.2882510333065,
            1.2069301257937188
        ],
        "policyset": [
            [
                [
                    [
                        0,
                        1
                    ],
                    [
                        -1,
                        0
                    ],
                    [
                        0,
                        -1
                    ]
                ],
                [
                    [
                        1,
                        0
                    ],
                    [
                        0,
                        -1
                    ],
                    [
                        0,
                        -1
                    ]
                ],
                [
                    [
                        0,
                        1
                    ],
                    [
                        1,
                        0
                    ],
                    [
                        0,
                        1
                    ]
                ]
            ],
            [
                [
                    [
                        1,
                        0
                    ],
                    [
                        0,
                        -1
                    ],
                    [
                        -1,
                        0
                    ]
                ],
                [
                    [
                        -1,
                        0
                    ],
                    [
                        0,
                        -1
                    ],
                    [
                        0,
                        -1
                    ]
                ],
                [
                    [
                        0,
                        1
                    ],
                    [
                        1,
                        0
                    ],
                    [
                        0,
                        1
                    ]
                ]
            ],
            [
                [
                    [
                        -1,
                        0
                    ],
                    [
                        0,
                        1
                    ],
                    [
                        1,
                        0
                    ]
                ],
                [
                    [
                        1,
                        0
                    ],
                    [
                        0,
                        -1
                    ],
                    [
                        0,
                        -1
                    ]
                ],
                [
                    [
                        0,
                        1
                    ],
                    [
                        1,
                        0
                    ],
                    [
                        0,
                        1
                    ]
                ]
            ]
        ],
        "converge": -1,
        "position": [
            [
                4,
                3
            ],
            [
                2,
                5
            ],
            [
                4,
                0
            ]
        ],
        "decision": [
            [
                [
                    1,
                    0
                ],
                [
                    0,
                    -1
                ],
                [
                    -1,
                    0
                ]
            ],
            [
                [
                    -1,
                    0
                ],
                [
                    0,
                    -1
                ],
                [
                    0,
                    -1
                ]
            ],
            [
                [
                    0,
                    1
                ],
                [
                    1,
                    0
                ],
                [
                    0,
                    1
                ]
            ]
        ],
        "gain": [
            0.13866575354409486,
            0.12025233881165036,
            0.1277896671854183
        ]
    },
    "14": {
        "values": [
            1.44801316678654
        ],
        "policyset": [
            [
                [
                    [
                        0,
                        1
                    ],
                    [
                        -1,
                        0
                    ],
                    [
                        -1,
                        0
                    ]
                ],
                [
                    [
                        0,
                        -1
                    ],
                    [
                        0,
                        -1
                    ],
                    [
                        -1,
                        0
                    ]
                ],
                [
                    [
                        1,
                        0
                    ],
                    [
                        0,
                        1
                    ],
                    [
                        0,
                        0
                    ]
                ]
            ]
        ],
        "converge": 0,
        "position": [
            [
                5,
                3
            ],
            [
                1,
                5
            ],
            [
                4,
                1
            ]
        ],
        "decision": [
            [
                [
                    0,
                    1
                ],
                [
                    -1,
                    0
                ],
                [
                    -1,
                    0
                ]
            ],
            [
                [
                    0,
                    -1
                ],
                [
                    0,
                    -1
                ],
                [
                    -1,
                    0
                ]
            ],
            [
                [
                    1,
                    0
                ],
                [
                    0,
                    1
                ],
                [
                    0,
                    0
                ]
            ]
        ],
        "gain": [
            0.14069349690016805,
            0.12862399613522033,
            0.11920467478779052
        ]
    },
    "15": {
        "values": [
            1.5029211103241118,
            1.3925598557910512,
            1.3925598557910512
        ],
        "policyset": [
            [
                [
                    [
                        -1,
                        0
                    ],
                    [
                        -1,
                        0
                    ],
                    [
                        0,
                        -1
                    ]
                ],
                [
                    [
                        0,
                        -1
                    ],
                    [
                        -1,
                        0
                    ],
                    [
                        0,
                        1
                    ]
                ],
                [
                    [
                        0,
                        1
                    ],
                    [
                        -1,
                        0
                    ],
                    [
                        -1,
                        0
                    ]
                ]
            ],
            [
                [
                    [
                        -1,
                        0
                    ],
                    [
                        -1,
                        0
                    ],
                    [
                        0,
                        -1
                    ]
                ],
                [
                    [
                        0,
                        -1
                    ],
                    [
                        0,
                        0
                    ],
                    [
                        -1,
                        0
                    ]
                ],
                [
                    [
                        0,
                        1
                    ],
                    [
                        0,
                        0
                    ],
                    [
                        0,
                        0
                    ]
                ]
            ],
            [
                [
                    [
                        -1,
                        0
                    ],
                    [
                        -1,
                        0
                    ],
                    [
                        0,
                        -1
                    ]
                ],
                [
                    [
                        0,
                        -1
                    ],
                    [
                        -1,
                        0
                    ],
                    [
                        1,
                        0
                    ]
                ],
                [
                    [
                        0,
                        1
                    ],
                    [
                        0,
                        0
                    ],
                    [
                        0,
                        0
                    ]
                ]
            ]
        ],
        "converge": -1,
        "position": [
            [
                5,
                4
            ],
            [
                1,
                4
            ],
            [
                5,
                1
            ]
        ],
        "decision": [
            [
                [
                    -1,
                    0
                ],
                [
                    -1,
                    0
                ],
                [
                    0,
                    -1
                ]
            ],
            [
                [
                    0,
                    -1
                ],
                [
                    -1,
                    0
                ],
                [
                    0,
                    1
                ]
            ],
            [
                [
                    0,
                    1
                ],
                [
                    -1,
                    0
                ],
                [
                    -1,
                    0
                ]
            ]
        ],
        "gain": [
            0.15446285694666656,
            0.19451527466050347,
            0.23174449478487308
        ]
    },
    "16": {
        "values": [
            1.2065872839369307,
            1.2021905345641495
        ],
        "policyset": [
            [
                [
                    [
                        -1,
                        0
                    ],
                    [
                        0,
                        -1
                    ],
                    [
                        0,
                        -1
                    ]
                ],
                [
                    [
                        -1,
                        0
                    ],
                    [
                        0,
                        1
                    ],
                    [
                        0,
                        1
                    ]
                ],
                [
                    [
                        -1,
                        0
                    ],
                    [
                        -1,
                        0
                    ],
                    [
                        0,
                        1
                    ]
                ]
            ],
            [
                [
                    [
                        -1,
                        0
                    ],
                    [
                        0,
                        -1
                    ],
                    [
                        0,
                        1
                    ]
                ],
                [
                    [
                        0,
                        -1
                    ],
                    [
                        0,
                        -1
                    ],
                    [
                        0,
                        0
                    ]
                ],
                [
                    [
                        -1,
                        0
                    ],
                    [
                        -1,
                        0
                    ],
                    [
                        0,
                        1
                    ]
                ]
            ]
        ],
        "converge": 1,
        "position": [
            [
                4,
                4
            ],
            [
                1,
                3
            ],
            [
                5,
                2
            ]
        ],
        "decision": [
            [
                [
                    -1,
                    0
                ],
                [
                    0,
                    -1
                ],
                [
                    0,
                    1
                ]
            ],
            [
                [
                    0,
                    -1
                ],
                [
                    0,
                    -1
                ],
                [
                    0,
                    0
                ]
            ],
            [
                [
                    -1,
                    0
                ],
                [
                    -1,
                    0
                ],
                [
                    0,
                    1
                ]
            ]
        ],
        "gain": [
            0.19559639064736944,
            0.12112474565144947,
            0.11158258600451265
        ]
    },
    "17": {
        "values": [
            1.1377512357292012,
            1.0835884646998997,
            1.1839197065599862
        ],
        "policyset": [
            [
                [
                    [
                        0,
                        -1
                    ],
                    [
                        0,
                        -1
                    ],
                    [
                        -1,
                        0
                    ]
                ],
                [
                    [
                        0,
                        -1
                    ],
                    [
                        -1,
                        0
                    ],
                    [
                        0,
                        -1
                    ]
                ],
                [
                    [
                        0,
                        1
                    ],
                    [
                        -1,
                        0
                    ],
                    [
                        0,
                        -1
                    ]
                ]
            ],
            [
                [
                    [
                        0,
                        -1
                    ],
                    [
                        0,
                        -1
                    ],
                    [
                        0,
                        1
                    ]
                ],
                [
                    [
                        0,
                        -1
                    ],
                    [
                        -1,
                        0
                    ],
                    [
                        0,
                        -1
                    ]
                ],
                [
                    [
                        -1,
                        0
                    ],
                    [
                        0,
                        1
                    ],
                    [
                        1,
                        0
                    ]
                ]
            ],
            [
                [
                    [
                        0,
                        -1
                    ],
                    [
                        0,
                        1
                    ],
                    [
                        0,
                        1
                    ]
                ],
                [
                    [
                        0,
                        -1
                    ],
                    [
                        -1,
                        0
                    ],
                    [
                        0,
                        -1
                    ]
                ],
                [
                    [
                        -1,
                        0
                    ],
                    [
                        0,
                        1
                    ],
                    [
                        1,
                        0
                    ]
                ]
            ]
        ],
        "converge": -1,
        "position": [
            [
                3,
                4
            ],
            [
                1,
                2
            ],
            [
                4,
                2
            ]
        ],
        "decision": [
            [
                [
                    0,
                    -1
                ],
                [
                    0,
                    1
                ],
                [
                    0,
                    1
                ]
            ],
            [
                [
                    0,
                    -1
                ],
                [
                    -1,
                    0
                ],
                [
                    0,
                    -1
                ]
            ],
            [
                [
                    -1,
                    0
                ],
                [
                    0,
                    1
                ],
                [
                    1,
                    0
                ]
            ]
        ],
        "gain": [
            0.17787509580122018,
            0.18709387915278364,
            0.12863515450612756
        ]
    },
    "18": {
        "values": [
            1.0361395943333158
        ],
        "policyset": [
            [
                [
                    [
                        0,
                        1
                    ],
                    [
                        0,
                        1
                    ],
                    [
                        -1,
                        0
                    ]
                ],
                [
                    [
                        -1,
                        0
                    ],
                    [
                        0,
                        -1
                    ],
                    [
                        0,
                        0
                    ]
                ],
                [
                    [
                        -1,
                        0
                    ],
                    [
                        0,
                        -1
                    ],
                    [
                        0,
                        -1
                    ]
                ]
            ]
        ],
        "converge": 0,
        "position": [
            [
                3,
                3
            ],
            [
                1,
                1
            ],
            [
                3,
                2
            ]
        ],
        "decision": [
            [
                [
                    0,
                    1
                ],
                [
                    0,
                    1
                ],
                [
                    -1,
                    0
                ]
            ],
            [
                [
                    -1,
                    0
                ],
                [
                    0,
                    -1
                ],
                [
                    0,
                    0
                ]
            ],
            [
                [
                    -1,
                    0
                ],
                [
                    0,
                    -1
                ],
                [
                    0,
                    -1
                ]
            ]
        ],
        "gain": [
            0.09779819532368472,
            0.06509011877273997,
            0.0986315449796066
        ]
    },
    "19": {
        "values": [
            0.9466129706095678,
            0.995690422009482
        ],
        "policyset": [
            [
                [
                    [
                        0,
                        1
                    ],
                    [
                        1,
                        0
                    ],
                    [
                        1,
                        0
                    ]
                ],
                [
                    [
                        0,
                        1
                    ],
                    [
                        0,
                        1
                    ],
                    [
                        0,
                        1
                    ]
                ],
                [
                    [
                        -1,
                        0
                    ],
                    [
                        0,
                        1
                    ],
                    [
                        -1,
                        0
                    ]
                ]
            ],
            [
                [
                    [
                        0,
                        1
                    ],
                    [
                        1,
                        0
                    ],
                    [
                        1,
                        0
                    ]
                ],
                [
                    [
                        0,
                        -1
                    ],
                    [
                        0,
                        0
                    ],
                    [
                        0,
                        0
                    ]
                ],
                [
                    [
                        0,
                        -1
                    ],
                    [
                        0,
                        -1
                    ],
                    [
                        0,
                        0
                    ]
                ]
            ]
        ],
        "converge": 1,
        "position": [
            [
                3,
                4
            ],
            [
                0,
                1
            ],
            [
                2,
                2
            ]
        ],
        "decision": [
            [
                [
                    0,
                    1
                ],
                [
                    1,
                    0
                ],
                [
                    1,
                    0
                ]
            ],
            [
                [
                    0,
                    -1
                ],
                [
                    0,
                    0
                ],
                [
                    0,
                    0
                ]
            ],
            [
                [
                    0,
                    -1
                ],
                [
                    0,
                    -1
                ],
                [
                    0,
                    0
                ]
            ]
        ],
        "gain": [
            0.11131939773977068,
            0.2235945671097268,
            0.06105878121797757
        ]
    },
    "t": 0.27723217010498047
}